Metadata-Version: 1.1
Name: jupyterlab-data-binding
Version: 0.1.0a0
Summary: Jupyterlab data binding demo
Home-page: https://github.com/hansnow/jupyterlab-data-binding
Author: Hansnow
Author-email: hansnow2012@gmail.com
License: UNKNOWN
Keywords: ipython,jupyter,widgets
Platform: UNKNOWN
Classifier: Development Status :: 4 - Beta
Classifier: Framework :: IPython
Classifier: Intended Audience :: Developers
Classifier: Intended Audience :: Science/Research
Classifier: Topic :: Multimedia :: Graphics
Classifier: Programming Language :: Python :: 2
Classifier: Programming Language :: Python :: 2.7
Classifier: Programming Language :: Python :: 3
Classifier: Programming Language :: Python :: 3.3
Classifier: Programming Language :: Python :: 3.4
Classifier: Programming Language :: Python :: 3.5
